netbox_scion/__init__.py
netbox_scion/admin.py
netbox_scion/filtersets.py
netbox_scion/forms.py
netbox_scion/models.py
netbox_scion/navigation.py
netbox_scion/search.py
netbox_scion/tables.py
netbox_scion/urls.py
netbox_scion/views.py
netbox_scion/api/__init__.py
netbox_scion/api/serializers.py
netbox_scion/api/urls.py
netbox_scion/api/views.py
netbox_scion/migrations/0001_initial.py
netbox_scion/migrations/__init__.py
netbox_scion/templates/netbox_scion/add_core.html
netbox_scion/templates/netbox_scion/isdas.csv
netbox_scion/templates/netbox_scion/isdas.html
netbox_scion/templates/netbox_scion/isdas_detail.html
netbox_scion/templates/netbox_scion/organization.csv
netbox_scion/templates/netbox_scion/organization.html
netbox_scion/templates/netbox_scion/organization_detail.html
netbox_scion/templates/netbox_scion/scionlink.csv
netbox_scion/templates/netbox_scion/scionlink.html
netbox_scion/templates/netbox_scion/scionlink_detail.html
netbox_scion/templates/netbox_scion/scionlink_edit.html
netbox_scion-1.4.dist-info/licenses/LICENSE
netbox_scion-1.4.dist-info/METADATA
netbox_scion-1.4.dist-info/WHEEL
netbox_scion-1.4.dist-info/top_level.txt
netbox_scion-1.4.dist-info/RECORD
