Metadata-Version: 2.4
Name: netbox_scion
Version: 1.4
Summary: NetBox plugin for managing SCION Links
Home-page: https://github.com/anapaya/netbox-scion
Author: Anapaya Systems AG
Author-email: Anapaya Systems AG <ops@anapaya.net>
License: Apache-2.0
Project-URL: Homepage, https://github.com/anapaya/netbox-scion
Project-URL: Source, https://github.com/anapaya/netbox-scion
Project-URL: Issues, https://github.com/anapaya/netbox-scion/issues
Keywords: netbox,plugin,scion
Classifier: Development Status :: 5 - Production/Stable
Classifier: Environment :: Web Environment
Classifier: Intended Audience :: Developers
Classifier: License :: OSI Approved :: Apache Software License
Classifier: Operating System :: OS Independent
Classifier: Programming Language :: Python :: 3
Classifier: Programming Language :: Python :: 3.8
Classifier: Programming Language :: Python :: 3.9
Classifier: Programming Language :: Python :: 3.10
Classifier: Programming Language :: Python :: 3.11
Classifier: Framework :: Django
Classifier: Topic :: Internet :: WWW/HTTP
Classifier: Topic :: Internet :: WWW/HTTP :: Dynamic Content
Requires-Python: >=3.8
License-File: LICENSE
Dynamic: author
Dynamic: home-page
Dynamic: license-file
Dynamic: requires-python
